swarmauri_middleware_circuitbreaker/CircuitBreakerMiddleware.py
swarmauri_middleware_circuitbreaker/__init__.py
swarmauri_middleware_circuitbreaker-0.7.0.dev4.dist-info/LICENSE
swarmauri_middleware_circuitbreaker-0.7.0.dev4.dist-info/METADATA
swarmauri_middleware_circuitbreaker-0.7.0.dev4.dist-info/WHEEL
swarmauri_middleware_circuitbreaker-0.7.0.dev4.dist-info/entry_points.txt
swarmauri_middleware_circuitbreaker-0.7.0.dev4.dist-info/RECORD
